save_skype/__init__.py
save_skype/extract.py
save_skype/format_msg.py
save_skype-0.1.5.dist-info/LICENSE
save_skype-0.1.5.dist-info/METADATA
save_skype-0.1.5.dist-info/WHEEL
save_skype-0.1.5.dist-info/entry_points.txt
save_skype-0.1.5.dist-info/top_level.txt
save_skype-0.1.5.dist-info/zip-safe
save_skype-0.1.5.dist-info/RECORD
