Metadata-Version: 2.1
Name: save-skype
Version: 0.1.5
Summary: Extract and save Skype chats.
Home-page: https://github.com/thismachinechills/save_skype
Author: thismachinechills (Alex)
Author-email: UNKNOWN
License: AGPL 3.0
Keywords: skype,main.db,extract,chats
Platform: UNKNOWN
Requires-Dist: click
Requires-Dist: html-wrapper
